{
  "Bash -> Выражения для проверки строк": {
    "строка1 < строка2": "строка1 меньше, чем строка2, в смысле алфавитной сортировки",
    "-n": "строка Длина строки больше нуля",
    "строка1 != строка2": "строка1 и строка2 не равны",
    "строка1 = строка2; строка1 == строка2": "строка1 и строка2 равны. Допускается использовать один или два знака «равно», но предпочтительнее два",
    "строка": "Cтрока не пустая",
    "строка1 > строка2": "строка1 больше, чем строка2, в смысле алфавитной сортировки",
    "-z": "строка Длина строки равна нулю",
    "строка1 =~ регулярное_выражение": "возвращающее истинное значение, если строка1 соответствует расширенному регулярному выражению [[]]"
  }
}